[{"Id":1,"UserId":4,"LoginDate":"2025-03-24T16:55:56.0922431-04:00","LogoutDate":"2025-03-24T16:56:00.2606249-04:00","IpAddress":"::1","City":"","RegionName":"","CountryCode":""},{"Id":2,"UserId":4,"LoginDate":"2025-03-24T16:56:53.9533355-04:00","LogoutDate":"2025-03-24T17:12:00.1922777-04:00","IpAddress":"::1","City":"","RegionName":"","CountryCode":""},{"Id":3,"UserId":4,"LoginDate":"2025-03-24T18:36:19.649833-04:00","LogoutDate":"2025-03-24T18:54:35.7972994-04:00","IpAddress":"::1","City":"","RegionName":"","CountryCode":""},{"Id":4,"UserId":4,"LoginDate":"2025-03-24T19:42:43.6903641-04:00","LogoutDate":"2025-03-24T19:42:43.6903641-04:00","IpAddress":"::1","City":"","RegionName":"","CountryCode":""},{"Id":5,"UserId":4,"LoginDate":"2025-03-24T19:53:42.1773277-04:00","LogoutDate":"2025-03-24T19:53:42.1773277-04:00","IpAddress":"::1","City":"","RegionName":"","CountryCode":""},{"Id":6,"UserId":4,"LoginDate":"2025-03-24T19:55:25.5586555-04:00","LogoutDate":"2025-03-24T19:55:25.5586555-04:00","IpAddress":"::1","City":"","RegionName":"","CountryCode":""},{"Id":7,"UserId":4,"LoginDate":"2025-03-24T20:06:40.7020191-04:00","LogoutDate":"2025-03-24T20:06:40.7020191-04:00","IpAddress":"::1","City":"","RegionName":"","CountryCode":""},{"Id":8,"UserId":4,"LoginDate":"2025-03-24T20:18:45.8530904-04:00","LogoutDate":"2025-03-24T20:33:57.9414784-04:00","IpAddress":"::1","City":"","RegionName":"","CountryCode":""},{"Id":9,"UserId":4,"LoginDate":"2025-03-25T18:30:02.1886895-04:00","LogoutDate":"2025-03-25T18:30:02.1886895-04:00","IpAddress":"::1","City":"","RegionName":"","CountryCode":""},{"Id":10,"UserId":4,"LoginDate":"2025-03-25T18:31:53.8568445-04:00","LogoutDate":"2025-03-25T18:32:35.3200498-04:00","IpAddress":"::1","City":"","RegionName":"","CountryCode":""},{"Id":11,"UserId":4,"LoginDate":"2025-03-25T18:33:33.9184085-04:00","LogoutDate":"2025-03-25T18:38:01.6654241-04:00","IpAddress":"::1","City":"","RegionName":"","CountryCode":""},{"Id":12,"UserId":4,"LoginDate":"2025-03-25T18:39:16.6776936-04:00","LogoutDate":"2025-03-25T18:41:10.9156805-04:00","IpAddress":"::1","City":"","RegionName":"","CountryCode":""},{"Id":13,"UserId":2,"LoginDate":"2025-03-25T18:43:39.6803516-04:00","LogoutDate":"2025-03-25T18:45:19.5827846-04:00","IpAddress":"::1","City":"","RegionName":"","CountryCode":""},{"Id":14,"UserId":4,"LoginDate":"2025-03-25T18:44:19.5170968-04:00","LogoutDate":"2025-03-25T19:00:44.9607537-04:00","IpAddress":"::1","City":"","RegionName":"","CountryCode":""},{"Id":15,"UserId":2,"LoginDate":"2025-03-25T18:45:29.5113493-04:00","LogoutDate":"2025-03-25T19:00:34.5837596-04:00","IpAddress":"::1","City":"","RegionName":"","CountryCode":""}]
